scrapyapi/__init__.py
scrapyapi/app/__init__.py
scrapyapi/app/main.py
scrapyapi/core/__init__.py
scrapyapi-0.0.1.dist-info/LICENSE
scrapyapi-0.0.1.dist-info/METADATA
scrapyapi-0.0.1.dist-info/WHEEL
scrapyapi-0.0.1.dist-info/entry_points.txt
scrapyapi-0.0.1.dist-info/top_level.txt
scrapyapi-0.0.1.dist-info/RECORD
